odoo9_addon_purchase_request_qweb_operating_unit-9.0.1.0.0.99.dev2-py2.7-nspkg.pth
odoo9_addon_purchase_request_qweb_operating_unit-9.0.1.0.0.99.dev2.dist-info/DESCRIPTION.rst
odoo9_addon_purchase_request_qweb_operating_unit-9.0.1.0.0.99.dev2.dist-info/METADATA
odoo9_addon_purchase_request_qweb_operating_unit-9.0.1.0.0.99.dev2.dist-info/RECORD
odoo9_addon_purchase_request_qweb_operating_unit-9.0.1.0.0.99.dev2.dist-info/WHEEL
odoo9_addon_purchase_request_qweb_operating_unit-9.0.1.0.0.99.dev2.dist-info/metadata.json
odoo9_addon_purchase_request_qweb_operating_unit-9.0.1.0.0.99.dev2.dist-info/namespace_packages.txt
odoo9_addon_purchase_request_qweb_operating_unit-9.0.1.0.0.99.dev2.dist-info/top_level.txt
odoo_addons/purchase_request_qweb_operating_unit/README.rst
odoo_addons/purchase_request_qweb_operating_unit/__init__.py
odoo_addons/purchase_request_qweb_operating_unit/__openerp__.py
odoo_addons/purchase_request_qweb_operating_unit/static/description/icon.png
odoo_addons/purchase_request_qweb_operating_unit/views/report_purchase_request_qweb.xml
