Metadata-Version: 2.0
Name: odoo9-addon-purchase-request-qweb-operating-unit
Version: 9.0.1.0.0.99.dev2
Summary: Purchase Request Qweb Report With Operating Unit
Home-page: https://odoo-community.org/
Author: Eficent Business and IT Consulting Services S.L., Serpent Consulting Services Pvt. Ltd.,Odoo Community Association (OCA)
Author-email: support@odoo-community.org
License: AGPL-3
Platform: UNKNOWN
Classifier: Programming Language :: Python
Classifier: Framework :: Odoo
Classifier: License :: OSI Approved :: GNU Affero General Public License v3
Requires-Python: ~=2.7
Requires-Dist: odoo (<9.1a,>=9.0a)
Requires-Dist: odoo9-addon-purchase-request-operating-unit
Requires-Dist: odoo9-addon-report-qweb-operating-unit
